{
  "posts": [
    {
      "id": 1,
      "title": "json-server",
      "author": "typicode"
    },
    {
      "title": "Minha primeira requisição",
      "author": "keven",
      "id": 2
    }
  ],
  "todos": [
    {
      "isDone": false,
      "name": "aa",
      "id": 13
    },
    {
      "isDone": false,
      "name": "aaaa",
      "id": 15
    },
    {
      "isDone": true,
      "name": "1",
      "id": 16
    },
    {
      "isDone": true,
      "name": "2",
      "id": 17
    }
  ],
  "comments": [
    {
      "id": 1,
      "body": "some comment",
      "postId": 1
    }
  ],
  "profile": {
    "name": "typicode"
  }
}